yetanotherpackage/__init__.py
yetanotherpackage/sum.py
yetanotherpackage-0.1.2.dist-info/WHEEL
yetanotherpackage-0.1.2.dist-info/entry_points.txt
yetanotherpackage-0.1.2.dist-info/METADATA
yetanotherpackage-0.1.2.dist-info/RECORD
